numpipe/__init__.py
numpipe/config.py
numpipe/display.py
numpipe/execution.py
numpipe/fileio.py
numpipe/h5cache.py
numpipe/mpl_tools.py
numpipe/networking.py
numpipe/notify.py
numpipe/numpipe.py
numpipe/parameters.py
numpipe/parser.py
numpipe/progress.py
numpipe/server.py
numpipe/slurm.py
numpipe/utility.py
numpipe-0.3.3.dist-info/LICENSE.md
numpipe-0.3.3.dist-info/METADATA
numpipe-0.3.3.dist-info/WHEEL
numpipe-0.3.3.dist-info/top_level.txt
numpipe-0.3.3.dist-info/RECORD
