Metadata-Version: 2.1
Name: numpipe
Version: 0.3.3
Summary: Easily run Python functions in parallel and cache the results
Home-page: UNKNOWN
Author: John Parker
Author-email: japarker@uchicago.edu
License: MIT
Keywords: cache pipeline hdf5 parallel cluster
Platform: UNKNOWN
Classifier: License :: OSI Approved :: MIT License
Classifier: Programming Language :: Python
Classifier: Operating System :: POSIX
Classifier: Operating System :: MacOS
Classifier: Development Status :: 3 - Alpha
Requires-Dist: numpy
Requires-Dist: h5py
Requires-Dist: termcolor
Requires-Dist: toml
Requires-Dist: matplotlib
Requires-Dist: tqdm
Requires-Dist: colorama
Requires-Dist: python-telegram-bot
